yolov5windowdetect/LICENSE
yolov5windowdetect/README.MD
yolov5windowdetect/__init__.py
yolov5windowdetect/requirements.txt
yolov5windowdetect/thirdparty.json
yolov5windowdetect-0.11.dist-info/LICENSE.rst
yolov5windowdetect-0.11.dist-info/METADATA
yolov5windowdetect-0.11.dist-info/WHEEL
yolov5windowdetect-0.11.dist-info/top_level.txt
yolov5windowdetect-0.11.dist-info/RECORD
