Metadata-Version: 2.1
Name: yolov5windowdetect
Version: 0.11
Summary: Capture window - run yolov5 - show results (Windows only)
Home-page: https://github.com/hansalemaos/yolov5windowdetect
Author: Johannes Fischer
Author-email: <aulasparticularesdealemaosp@gmail.com>
License: MIT
Keywords: yolov5,yolo,screenshot,pandas,dataframe
Classifier: Development Status :: 4 - Beta
Classifier: Programming Language :: Python :: 3 :: Only
Classifier: Programming Language :: Python :: 3.9
Classifier: Topic :: Scientific/Engineering :: Visualization
Classifier: Topic :: Software Development :: Libraries :: Python Modules
Classifier: Topic :: Text Editors :: Text Processing
Classifier: Topic :: Text Processing :: General
Classifier: Topic :: Text Processing :: Indexing
Classifier: Topic :: Text Processing :: Filters
Classifier: Topic :: Utilities
License-File: LICENSE.rst
Requires-Dist: keyboard
Requires-Dist: numpy
Requires-Dist: opencv-python
Requires-Dist: pandas
Requires-Dist: PILasOPENCV
Requires-Dist: PrettyColorPrinter
Requires-Dist: requests
Requires-Dist: torch
